wasmtime_executor/__init__.py
wasmtime_executor/executor.py
wasmtime_executor/wasm-runtime/bin/python-3.11.1.wasm
wasmtime_executor/wasm-runtime/usr/local/lib/python311.zip
wasmtime_executor-0.1.0.dist-info/METADATA
wasmtime_executor-0.1.0.dist-info/WHEEL
wasmtime_executor-0.1.0.dist-info/RECORD
