Metadata-Version: 2.4
Name: wasmtime-executor
Version: 0.1.0
Summary: A WASMTIME-based Python code executor for smolagents with sandboxed execution
Requires-Python: >=3.11
Requires-Dist: wasmtime>=24.0.0
